[
    {
        "activity":"branch_visit",
        "offer_id":"",
        "offer_name":"",
        "offer_url":"https://images.hdqwalls.com/wallpapers/baby-yoda-cute-5k-ef.jpg"
    },
    {
        "activity":"deposit",
        "offer_id":"",
        "offer_name":"",
        "offer_url":"https://images.hdqwalls.com/wallpapers/baby-yoda-cute-5k-ef.jpg"
    },
    {
        "activity":"web_open",
        "offer_id":"",
        "offer_name":"",
        "offer_url":"https://images.hdqwalls.com/wallpapers/baby-yoda-cute-5k-ef.jpg"
    },
    {
        "activity":"mobile_open",
        "offer_id":"",
        "offer_name":"",
        "offer_url":"https://images.hdqwalls.com/wallpapers/baby-yoda-cute-5k-ef.jpg"
    },
    {
        "activity":"new_account",
        "offer_id":"",
        "offer_name":"",
        "offer_url":"https://images.hdqwalls.com/wallpapers/baby-yoda-cute-5k-ef.jpg"
    }
]